indi/VERSION
indi/__init__.py
indi/logging.py
indi/client/__init__.py
indi/client/client.py
indi/client/device.py
indi/client/elements.py
indi/client/events.py
indi/client/vectors.py
indi/device/__init__.py
indi/device/driver.py
indi/device/events.py
indi/device/pool.py
indi/device/proxy.py
indi/device/snoop.py
indi/device/values.py
indi/device/properties/__init__.py
indi/device/properties/const.py
indi/device/properties/definition/__init__.py
indi/device/properties/definition/elements.py
indi/device/properties/definition/group.py
indi/device/properties/definition/vectors.py
indi/device/properties/instance/__init__.py
indi/device/properties/instance/elements.py
indi/device/properties/instance/group.py
indi/device/properties/instance/vectors.py
indi/device/properties/standard/__init__.py
indi/device/properties/standard/ccd.py
indi/device/properties/standard/common.py
indi/device/properties/standard/focuser.py
indi/message/__init__.py
indi/message/base.py
indi/message/checks.py
indi/message/const.py
indi/message/def_parts.py
indi/message/defs.py
indi/message/del_property.py
indi/message/enable_blob.py
indi/message/get_properties.py
indi/message/news.py
indi/message/one_light.py
indi/message/one_parts.py
indi/message/pings.py
indi/message/sets.py
indi/routing/__init__.py
indi/routing/client.py
indi/routing/device.py
indi/routing/router.py
indi/transport/__init__.py
indi/transport/buffer.py
indi/transport/client/__init__.py
indi/transport/client/tcp.py
indi/transport/server/__init__.py
indi/transport/server/tcp.py
indi/transport/server/tty.py
INDIpy-0.4.0.dist-info/METADATA
INDIpy-0.4.0.dist-info/WHEEL
INDIpy-0.4.0.dist-info/top_level.txt
INDIpy-0.4.0.dist-info/RECORD
