Metadata-Version: 2.1
Name: INDIpy
Version: 0.4.0
Summary: Python implementation of INDI server and client
Home-page: http://github.com/wlatanowicz/indipy
Author: Wiktor Latanowicz
Author-email: indipy@wiktor.latanowicz.com
License: MIT
Classifier: Programming Language :: Python :: 3
Classifier: License :: OSI Approved :: MIT License
Classifier: Operating System :: OS Independent
Requires-Python: >=3.7
Requires-Dist: aiofiles
